LICENSE.txt
README.md
setup.py
linear_mahdi/linear_mahdi.py
linear_mahdi.egg-info/PKG-INFO
linear_mahdi.egg-info/SOURCES.txt
linear_mahdi.egg-info/dependency_links.txt
linear_mahdi.egg-info/requires.txt
linear_mahdi.egg-info/top_level.txt